qualyspy/URLS.py
qualyspy/__init__.py
qualyspy/asset_mgmt_tagging.py
qualyspy/base.py
qualyspy/certview.py
qualyspy/exceptions.py
qualyspy/gav.py
qualyspy/qualyspy_logging.py
qualyspy/qutils.py
qualyspy/vmdr.py
qualyspy/models/__init__.py
qualyspy/models/sa_types.py
qualyspy/models/asset_mgmt_tagging/__init__.py
qualyspy/models/asset_mgmt_tagging/asset_output.py
qualyspy/models/asset_mgmt_tagging/asset_request.py
qualyspy/models/asset_mgmt_tagging/tag_output.py
qualyspy/models/asset_mgmt_tagging/tag_request.py
qualyspy/models/certview/instances_orm.py
qualyspy/models/certview/instances_output.py
qualyspy/models/gav/__init__.py
qualyspy/models/gav/asset_details_orm.py
qualyspy/models/gav/asset_details_output.py
qualyspy/models/vmdr/__init__.py
qualyspy/models/vmdr/asset_group_list_output.py
qualyspy/models/vmdr/host_list_orm.py
qualyspy/models/vmdr/host_list_output.py
qualyspy/models/vmdr/host_list_vm_detection_orm.py
qualyspy/models/vmdr/host_list_vm_detection_output.py
qualyspy/models/vmdr/knowledgebase_orm.py
qualyspy/models/vmdr/knowledgebase_output.py
qualyspy/models/vmdr/map_report.py
qualyspy/models/vmdr/map_report_list.py
qualyspy/models/vmdr/scan_list_output.py
qualyspy/models/vmdr/simple_return.py
qualyspy-0.5.10.6.dist-info/METADATA
qualyspy-0.5.10.6.dist-info/WHEEL
qualyspy-0.5.10.6.dist-info/licenses/LICENSE
qualyspy-0.5.10.6.dist-info/RECORD
